Metadata-Version: 1.0
Name: disat
Version: 0.2
Summary: Gaussian distributions
Home-page: UNKNOWN
Author: Carson Rodrigues
Author-email: rodriguescarson@gmail.com
License: UNKNOWN
Platform: UNKNOWN
